office_assistant_mcp/__init__.py
office_assistant_mcp/brand_list_lower.txt
office_assistant_mcp/category.json
office_assistant_mcp/crowd_filter.py
office_assistant_mcp/crowd_filter_prompts.py
office_assistant_mcp/mcp_server.py
office_assistant_mcp/playwright_message.py
office_assistant_mcp/playwright_util.py
office_assistant_mcp/prompt.py
shared/__init__.py
shared/browser_manager.py
shared/coze_api.py
shared/error_handler.py
shared/llm_util.py
shared/log_util.py
shared/mcp_session_manager.py
office_assistant_mcp-0.0.25.dist-info/METADATA
office_assistant_mcp-0.0.25.dist-info/WHEEL
office_assistant_mcp-0.0.25.dist-info/entry_points.txt
office_assistant_mcp-0.0.25.dist-info/top_level.txt
office_assistant_mcp-0.0.25.dist-info/RECORD
